{
  "subjects": [
    {
      "name": "Introduction to Computer Science",
      "description": "Fundamentals of computer systems, algorithms, and programming."
    },
    {
      "name": "Data Structures and Algorithms",
      "description": "Study of data organization, storage, and retrieval methods."
    },
    {
      "name": "Database Systems",
      "description": "Design and management of databases and database systems."
    },
    {
      "name": "Operating Systems",
      "description": "Principles and implementation of operating systems."
    },
    {
      "name": "Software Engineering",
      "description": "Principles and practices for developing software systems."
    },
    {
      "name": "Computer Networks",
      "description": "Fundamentals of computer networking and communication protocols."
    },
    {
      "name": "Artificial Intelligence",
      "description": "Study of intelligent agents, machine learning, and natural language processing."
    },
    {
      "name": "Cybersecurity",
      "description": "Principles and practices for securing computer systems and networks."
    },
    {
      "name": "Web Development",
      "description": "Development of web applications and technologies."
    },
    {
      "name": "Mobile Application Development",
      "description": "Development of mobile applications and technologies."
    }
  ]
}
